rawake/__init__.py
rawake/__main__.py
rawake/__version__.py
rawake/cli.py
rawake/computer_controller.py
rawake/config.py
rawake/logging.py
rawake/main.py
rawake-0.2.1.dist-info/LICENSE
rawake-0.2.1.dist-info/METADATA
rawake-0.2.1.dist-info/WHEEL
rawake-0.2.1.dist-info/entry_points.txt
rawake-0.2.1.dist-info/top_level.txt
rawake-0.2.1.dist-info/RECORD
